odoo8_addon_account_invoice_kanban-8.0.1.0.0.99.dev20-py2.7-nspkg.pth
odoo8_addon_account_invoice_kanban-8.0.1.0.0.99.dev20.dist-info/METADATA
odoo8_addon_account_invoice_kanban-8.0.1.0.0.99.dev20.dist-info/RECORD
odoo8_addon_account_invoice_kanban-8.0.1.0.0.99.dev20.dist-info/WHEEL
odoo8_addon_account_invoice_kanban-8.0.1.0.0.99.dev20.dist-info/namespace_packages.txt
odoo8_addon_account_invoice_kanban-8.0.1.0.0.99.dev20.dist-info/top_level.txt
odoo_addons/account_invoice_kanban/README.rst
odoo_addons/account_invoice_kanban/__init__.py
odoo_addons/account_invoice_kanban/__openerp__.py
odoo_addons/account_invoice_kanban/demo/account_invoice_demo.xml
odoo_addons/account_invoice_kanban/i18n/account_invoice_kanban.pot
odoo_addons/account_invoice_kanban/i18n/am.po
odoo_addons/account_invoice_kanban/i18n/ar.po
odoo_addons/account_invoice_kanban/i18n/bg.po
odoo_addons/account_invoice_kanban/i18n/bs.po
odoo_addons/account_invoice_kanban/i18n/ca.po
odoo_addons/account_invoice_kanban/i18n/ca_ES.po
odoo_addons/account_invoice_kanban/i18n/cs.po
odoo_addons/account_invoice_kanban/i18n/da.po
odoo_addons/account_invoice_kanban/i18n/da_DK.po
odoo_addons/account_invoice_kanban/i18n/de.po
odoo_addons/account_invoice_kanban/i18n/el_GR.po
odoo_addons/account_invoice_kanban/i18n/en_GB.po
odoo_addons/account_invoice_kanban/i18n/es.po
odoo_addons/account_invoice_kanban/i18n/es_AR.po
odoo_addons/account_invoice_kanban/i18n/es_CL.po
odoo_addons/account_invoice_kanban/i18n/es_CO.po
odoo_addons/account_invoice_kanban/i18n/es_CR.po
odoo_addons/account_invoice_kanban/i18n/es_DO.po
odoo_addons/account_invoice_kanban/i18n/es_EC.po
odoo_addons/account_invoice_kanban/i18n/es_ES.po
odoo_addons/account_invoice_kanban/i18n/es_MX.po
odoo_addons/account_invoice_kanban/i18n/es_PE.po
odoo_addons/account_invoice_kanban/i18n/es_PY.po
odoo_addons/account_invoice_kanban/i18n/es_VE.po
odoo_addons/account_invoice_kanban/i18n/et.po
odoo_addons/account_invoice_kanban/i18n/eu.po
odoo_addons/account_invoice_kanban/i18n/fa.po
odoo_addons/account_invoice_kanban/i18n/fi.po
odoo_addons/account_invoice_kanban/i18n/fr.po
odoo_addons/account_invoice_kanban/i18n/fr_CA.po
odoo_addons/account_invoice_kanban/i18n/fr_CH.po
odoo_addons/account_invoice_kanban/i18n/gl.po
odoo_addons/account_invoice_kanban/i18n/gl_ES.po
